<?xml version="1.0" encoding="UTF-8"?>
<mxfile host="app.diagrams.net" modified="2022-02-22T20:06:25.350Z" agent="5.0 (X11; Linux x86_64) AppleWebKit/537.36 (KHTML, like Gecko) Chrome/97.0.4692.99 Safari/537.36" etag="Ovk6ZTuahL_Cgkwl-osE" compressed="false" version="16.6.2">
  <diagram id="sDSvwKW63rh-0tk_r-xe" name="Page-1">
    <mxGraphModel dx="2004" dy="1171" grid="1" gridSize="10" guides="1" tooltips="1" connect="1" arrows="1" fold="1" page="1" pageScale="1" pageWidth="850" pageHeight="1100" math="0" shadow="0">
      <root>
        <mxCell id="0" />
        <mxCell id="1" parent="0" />
        <mxCell id="vZeMXZc9KxlSnCoKcg_M-1" value="" style="rounded=0;whiteSpace=wrap;html=1;" parent="1" vertex="1">
          <mxGeometry x="385" y="510" width="80" height="80" as="geometry" />
        </mxCell>
        <mxCell id="vZeMXZc9KxlSnCoKcg_M-2" value="" style="rounded=0;whiteSpace=wrap;html=1;" parent="1" vertex="1">
          <mxGeometry x="625" y="510" width="80" height="80" as="geometry" />
        </mxCell>
        <mxCell id="vZeMXZc9KxlSnCoKcg_M-3" value="" style="rounded=0;whiteSpace=wrap;html=1;" parent="1" vertex="1">
          <mxGeometry x="145" y="510" width="80" height="80" as="geometry" />
        </mxCell>
        <mxCell id="vZeMXZc9KxlSnCoKcg_M-9" value="" style="rounded=0;whiteSpace=wrap;html=1;" parent="1" vertex="1">
          <mxGeometry x="145" y="350" width="80" height="80" as="geometry" />
        </mxCell>
        <mxCell id="vZeMXZc9KxlSnCoKcg_M-10" value="" style="rounded=0;whiteSpace=wrap;html=1;" parent="1" vertex="1">
          <mxGeometry x="385" y="350" width="80" height="80" as="geometry" />
        </mxCell>
        <mxCell id="vZeMXZc9KxlSnCoKcg_M-11" value="" style="rounded=0;whiteSpace=wrap;html=1;" parent="1" vertex="1">
          <mxGeometry x="625" y="350" width="80" height="80" as="geometry" />
        </mxCell>
        <mxCell id="vZeMXZc9KxlSnCoKcg_M-12" value="" style="rounded=0;whiteSpace=wrap;html=1;" parent="1" vertex="1">
          <mxGeometry x="145" y="670" width="80" height="80" as="geometry" />
        </mxCell>
        <mxCell id="vZeMXZc9KxlSnCoKcg_M-13" value="" style="rounded=0;whiteSpace=wrap;html=1;" parent="1" vertex="1">
          <mxGeometry x="385" y="670" width="80" height="80" as="geometry" />
        </mxCell>
        <mxCell id="vZeMXZc9KxlSnCoKcg_M-14" value="" style="rounded=0;whiteSpace=wrap;html=1;" parent="1" vertex="1">
          <mxGeometry x="625" y="670" width="80" height="80" as="geometry" />
        </mxCell>
      </root>
    </mxGraphModel>
  </diagram>
</mxfile>
