<?xml version="1.0" encoding="UTF-8"?>
<mxfile host="app.diagrams.net" modified="2022-03-01T17:43:10.051Z" agent="5.0 (X11; Linux x86_64) AppleWebKit/537.36 (KHTML, like Gecko) Chrome/97.0.4692.99 Safari/537.36" etag="v-ZpDtmjI5Pm2IxZWqzZ" compressed="false" version="16.6.2">
  <diagram id="sDSvwKW63rh-0tk_r-xe" name="Page-1">
    <mxGraphModel dx="525" dy="277" grid="1" gridSize="10" guides="1" tooltips="1" connect="1" arrows="1" fold="1" page="1" pageScale="1" pageWidth="850" pageHeight="1100" math="0" shadow="0">
      <root>
        <mxCell id="0" />
        <mxCell id="1" parent="0" />
        <mxCell id="c9b9Fy7ZHcx6M--AJpKg-1" value="" style="rounded=0;whiteSpace=wrap;html=1;" vertex="1" parent="1">
          <mxGeometry x="195" y="460" width="16" height="16" as="geometry" />
        </mxCell>
        <mxCell id="c9b9Fy7ZHcx6M--AJpKg-2" value="" style="rounded=0;whiteSpace=wrap;html=1;" vertex="1" parent="1">
          <mxGeometry x="259" y="460" width="16" height="16" as="geometry" />
        </mxCell>
        <mxCell id="c9b9Fy7ZHcx6M--AJpKg-3" value="" style="rounded=0;whiteSpace=wrap;html=1;" vertex="1" parent="1">
          <mxGeometry x="195" y="524" width="16" height="16" as="geometry" />
        </mxCell>
        <mxCell id="c9b9Fy7ZHcx6M--AJpKg-4" value="" style="rounded=0;whiteSpace=wrap;html=1;" vertex="1" parent="1">
          <mxGeometry x="259" y="524" width="16" height="16" as="geometry" />
        </mxCell>
        <mxCell id="c9b9Fy7ZHcx6M--AJpKg-5" value="" style="rounded=0;whiteSpace=wrap;html=1;" vertex="1" parent="1">
          <mxGeometry x="259" y="492" width="16" height="16" as="geometry" />
        </mxCell>
        <mxCell id="c9b9Fy7ZHcx6M--AJpKg-6" value="" style="rounded=0;whiteSpace=wrap;html=1;" vertex="1" parent="1">
          <mxGeometry x="195" y="492" width="16" height="16" as="geometry" />
        </mxCell>
        <mxCell id="c9b9Fy7ZHcx6M--AJpKg-7" value="" style="rounded=0;whiteSpace=wrap;html=1;" vertex="1" parent="1">
          <mxGeometry x="227" y="460" width="16" height="16" as="geometry" />
        </mxCell>
        <mxCell id="c9b9Fy7ZHcx6M--AJpKg-8" value="" style="rounded=0;whiteSpace=wrap;html=1;" vertex="1" parent="1">
          <mxGeometry x="227" y="524" width="16" height="16" as="geometry" />
        </mxCell>
        <mxCell id="c9b9Fy7ZHcx6M--AJpKg-9" value="" style="rounded=0;whiteSpace=wrap;html=1;" vertex="1" parent="1">
          <mxGeometry x="227" y="492" width="16" height="16" as="geometry" />
        </mxCell>
        <mxCell id="c9b9Fy7ZHcx6M--AJpKg-10" value="" style="rounded=0;whiteSpace=wrap;html=1;" vertex="1" parent="1">
          <mxGeometry x="135" y="560" width="16" height="16" as="geometry" />
        </mxCell>
        <mxCell id="c9b9Fy7ZHcx6M--AJpKg-11" value="" style="rounded=0;whiteSpace=wrap;html=1;" vertex="1" parent="1">
          <mxGeometry x="199" y="560" width="16" height="16" as="geometry" />
        </mxCell>
        <mxCell id="c9b9Fy7ZHcx6M--AJpKg-12" value="" style="rounded=0;whiteSpace=wrap;html=1;" vertex="1" parent="1">
          <mxGeometry x="135" y="624" width="16" height="16" as="geometry" />
        </mxCell>
        <mxCell id="c9b9Fy7ZHcx6M--AJpKg-13" value="" style="rounded=0;whiteSpace=wrap;html=1;" vertex="1" parent="1">
          <mxGeometry x="199" y="624" width="16" height="16" as="geometry" />
        </mxCell>
        <mxCell id="c9b9Fy7ZHcx6M--AJpKg-14" value="" style="rounded=0;whiteSpace=wrap;html=1;" vertex="1" parent="1">
          <mxGeometry x="199" y="592" width="16" height="16" as="geometry" />
        </mxCell>
        <mxCell id="c9b9Fy7ZHcx6M--AJpKg-15" value="" style="rounded=0;whiteSpace=wrap;html=1;" vertex="1" parent="1">
          <mxGeometry x="135" y="592" width="16" height="16" as="geometry" />
        </mxCell>
        <mxCell id="c9b9Fy7ZHcx6M--AJpKg-16" value="" style="rounded=0;whiteSpace=wrap;html=1;" vertex="1" parent="1">
          <mxGeometry x="167" y="560" width="16" height="16" as="geometry" />
        </mxCell>
        <mxCell id="c9b9Fy7ZHcx6M--AJpKg-17" value="" style="rounded=0;whiteSpace=wrap;html=1;" vertex="1" parent="1">
          <mxGeometry x="167" y="624" width="16" height="16" as="geometry" />
        </mxCell>
        <mxCell id="c9b9Fy7ZHcx6M--AJpKg-18" value="" style="rounded=0;whiteSpace=wrap;html=1;" vertex="1" parent="1">
          <mxGeometry x="167" y="592" width="16" height="16" as="geometry" />
        </mxCell>
        <mxCell id="c9b9Fy7ZHcx6M--AJpKg-19" value="" style="rounded=0;whiteSpace=wrap;html=1;" vertex="1" parent="1">
          <mxGeometry x="585" y="460" width="16" height="16" as="geometry" />
        </mxCell>
        <mxCell id="c9b9Fy7ZHcx6M--AJpKg-20" value="" style="rounded=0;whiteSpace=wrap;html=1;" vertex="1" parent="1">
          <mxGeometry x="649" y="460" width="16" height="16" as="geometry" />
        </mxCell>
        <mxCell id="c9b9Fy7ZHcx6M--AJpKg-21" value="" style="rounded=0;whiteSpace=wrap;html=1;" vertex="1" parent="1">
          <mxGeometry x="585" y="524" width="16" height="16" as="geometry" />
        </mxCell>
        <mxCell id="c9b9Fy7ZHcx6M--AJpKg-22" value="" style="rounded=0;whiteSpace=wrap;html=1;" vertex="1" parent="1">
          <mxGeometry x="649" y="524" width="16" height="16" as="geometry" />
        </mxCell>
        <mxCell id="c9b9Fy7ZHcx6M--AJpKg-23" value="" style="rounded=0;whiteSpace=wrap;html=1;" vertex="1" parent="1">
          <mxGeometry x="649" y="492" width="16" height="16" as="geometry" />
        </mxCell>
        <mxCell id="c9b9Fy7ZHcx6M--AJpKg-24" value="" style="rounded=0;whiteSpace=wrap;html=1;" vertex="1" parent="1">
          <mxGeometry x="585" y="492" width="16" height="16" as="geometry" />
        </mxCell>
        <mxCell id="c9b9Fy7ZHcx6M--AJpKg-25" value="" style="rounded=0;whiteSpace=wrap;html=1;" vertex="1" parent="1">
          <mxGeometry x="617" y="460" width="16" height="16" as="geometry" />
        </mxCell>
        <mxCell id="c9b9Fy7ZHcx6M--AJpKg-26" value="" style="rounded=0;whiteSpace=wrap;html=1;" vertex="1" parent="1">
          <mxGeometry x="617" y="524" width="16" height="16" as="geometry" />
        </mxCell>
        <mxCell id="c9b9Fy7ZHcx6M--AJpKg-27" value="" style="rounded=0;whiteSpace=wrap;html=1;" vertex="1" parent="1">
          <mxGeometry x="617" y="492" width="16" height="16" as="geometry" />
        </mxCell>
        <mxCell id="c9b9Fy7ZHcx6M--AJpKg-28" value="" style="rounded=0;whiteSpace=wrap;html=1;" vertex="1" parent="1">
          <mxGeometry x="645" y="560" width="16" height="16" as="geometry" />
        </mxCell>
        <mxCell id="c9b9Fy7ZHcx6M--AJpKg-29" value="" style="rounded=0;whiteSpace=wrap;html=1;" vertex="1" parent="1">
          <mxGeometry x="709" y="560" width="16" height="16" as="geometry" />
        </mxCell>
        <mxCell id="c9b9Fy7ZHcx6M--AJpKg-30" value="" style="rounded=0;whiteSpace=wrap;html=1;" vertex="1" parent="1">
          <mxGeometry x="645" y="624" width="16" height="16" as="geometry" />
        </mxCell>
        <mxCell id="c9b9Fy7ZHcx6M--AJpKg-31" value="" style="rounded=0;whiteSpace=wrap;html=1;" vertex="1" parent="1">
          <mxGeometry x="709" y="624" width="16" height="16" as="geometry" />
        </mxCell>
        <mxCell id="c9b9Fy7ZHcx6M--AJpKg-32" value="" style="rounded=0;whiteSpace=wrap;html=1;" vertex="1" parent="1">
          <mxGeometry x="709" y="592" width="16" height="16" as="geometry" />
        </mxCell>
        <mxCell id="c9b9Fy7ZHcx6M--AJpKg-33" value="" style="rounded=0;whiteSpace=wrap;html=1;" vertex="1" parent="1">
          <mxGeometry x="645" y="592" width="16" height="16" as="geometry" />
        </mxCell>
        <mxCell id="c9b9Fy7ZHcx6M--AJpKg-34" value="" style="rounded=0;whiteSpace=wrap;html=1;" vertex="1" parent="1">
          <mxGeometry x="677" y="560" width="16" height="16" as="geometry" />
        </mxCell>
        <mxCell id="c9b9Fy7ZHcx6M--AJpKg-35" value="" style="rounded=0;whiteSpace=wrap;html=1;" vertex="1" parent="1">
          <mxGeometry x="677" y="624" width="16" height="16" as="geometry" />
        </mxCell>
        <mxCell id="c9b9Fy7ZHcx6M--AJpKg-36" value="" style="rounded=0;whiteSpace=wrap;html=1;" vertex="1" parent="1">
          <mxGeometry x="677" y="592" width="16" height="16" as="geometry" />
        </mxCell>
      </root>
    </mxGraphModel>
  </diagram>
</mxfile>
